kss_cython.cpython-310-darwin.so
bench/sentence_split/__init__.py
bench/sentence_split/sentence_split.py
bench/sentence_split/test_baseline.py
bench/sentence_split/test_kiwi.py
bench/sentence_split/test_koalanlp.py
bench/sentence_split/test_kss.py
bench/sentence_split/test_word_split.py
csrc/__init__.py
csrc/kss_cython.pyx
csrc/sentence_splitter.cpp
csrc/sentence_splitter.h
kss/__init__.py
kss/_elements/__init__.py
kss/_elements/element.py
kss/_elements/empty.py
kss/_elements/subclasses.py
kss/_modules/__init__.py
kss/_modules/augmentation/__init__.py
kss/_modules/augmentation/augment.py
kss/_modules/augmentation/distance.py
kss/_modules/augmentation/replacement.py
kss/_modules/augmentation/utils.py
kss/_modules/augmentation/assets/wordnet.json
kss/_modules/collocation/__init__.py
kss/_modules/collocation/collocate.py
kss/_modules/g2p/__init__.py
kss/_modules/g2p/english.py
kss/_modules/g2p/g2p.py
kss/_modules/g2p/numerals.py
kss/_modules/g2p/regular.py
kss/_modules/g2p/special.py
kss/_modules/g2p/utils.py
kss/_modules/g2p/assets/idioms.txt
kss/_modules/g2p/assets/rules.txt
kss/_modules/g2p/assets/table.csv
kss/_modules/hangulization/__init__.py
kss/_modules/hangulization/hangulization.py
kss/_modules/hangulization/hangulize/__init__.py
kss/_modules/hangulization/hangulize/hangul.py
kss/_modules/hangulization/hangulize/models.py
kss/_modules/hangulization/hangulize/normalization.py
kss/_modules/hangulization/hangulize/processing.py
kss/_modules/hangulization/hangulize/langs/__init__.py
kss/_modules/hangulization/hangulize/langs/aze/__init__.py
kss/_modules/hangulization/hangulize/langs/bel/__init__.py
kss/_modules/hangulization/hangulize/langs/bul/__init__.py
kss/_modules/hangulization/hangulize/langs/cat/__init__.py
kss/_modules/hangulization/hangulize/langs/ces/__init__.py
kss/_modules/hangulization/hangulize/langs/cym/__init__.py
kss/_modules/hangulization/hangulize/langs/deu/__init__.py
kss/_modules/hangulization/hangulize/langs/ell/__init__.py
kss-6.0.6.dist-info/licenses/LICENSE
kss-6.0.6.dist-info/METADATA
kss-6.0.6.dist-info/WHEEL
kss-6.0.6.dist-info/top_level.txt
kss-6.0.6.dist-info/RECORD
