Metadata-Version: 2.4
Name: kss
Version: 6.0.6
Summary: A Toolkit for Korean sentence segmentation
Home-page: https://github.com/hyunwoongko/kss
Author: Hyunwoong Ko
Author-email: kevin.brain@kakaobrain.com
License: BSD 3-Clause "New" or "Revised" License
Platform: any
Classifier: Programming Language :: Python :: 3
Classifier: Programming Language :: Python :: 3.2
Classifier: Programming Language :: Python :: 3.3
Classifier: Programming Language :: Python :: 3.4
Classifier: Programming Language :: Python :: 3.5
Classifier: Programming Language :: Python :: 3.6
Classifier: Programming Language :: Python :: 3.7
Classifier: Programming Language :: Python :: 3.8
Requires-Python: >=3
License-File: LICENSE
Requires-Dist: emoji==1.2.0
Requires-Dist: pecab
Requires-Dist: networkx
Requires-Dist: jamo
Requires-Dist: hangul-jamo
Requires-Dist: tossi
Requires-Dist: distance
Requires-Dist: pyyaml>=6.0.2
Requires-Dist: unidecode
Requires-Dist: cmudict
Requires-Dist: koparadigm
Requires-Dist: kollocate
Requires-Dist: bs4
Requires-Dist: numpy
Requires-Dist: pytest
Requires-Dist: scipy
Dynamic: author
Dynamic: author-email
Dynamic: classifier
Dynamic: description
Dynamic: description-content-type
Dynamic: home-page
Dynamic: license
Dynamic: license-file
Dynamic: platform
Dynamic: requires-dist
Dynamic: requires-python
Dynamic: summary
